markdown_ansi/__init__.py
markdown_ansi/ansi.py
markdown_ansi-0.1.0.dist-info/WHEEL
markdown_ansi-0.1.0.dist-info/METADATA
markdown_ansi-0.1.0.dist-info/RECORD
