Metadata-Version: 2.1
Name: markdown-ansi
Version: 0.1.0
License: MIT
Author-email: Jan Graichen <jgraichen@altimos.de>
Requires-Python: >=3.8
Requires-Dist: ansi2html>=1.8.0
